gantrainer/__init__.py
gantrainer/train.py
genai_util_bin-0.1.0.dist-info/METADATA
genai_util_bin-0.1.0.dist-info/WHEEL
genai_util_bin-0.1.0.dist-info/entry_points.txt
genai_util_bin-0.1.0.dist-info/top_level.txt
genai_util_bin-0.1.0.dist-info/RECORD
